MANIFEST.in
VERSION
setup.py
docs/source/conf.py
ibrb.ext.clients.egg-info/PKG-INFO
ibrb.ext.clients.egg-info/SOURCES.txt
ibrb.ext.clients.egg-info/dependency_links.txt
ibrb.ext.clients.egg-info/requires.txt
ibrb.ext.clients.egg-info/top_level.txt
ibrb/ext/clients/__init__.py
ibrb/ext/clients/base.py
ibrb/ext/clients/clienttestcase.py
ibrb/ext/clients/package.json
ibrb/ext/clients/utils.py
ibrb/ext/clients/tests/__init__.py
ibrb/ext/clients/tests/test_integration_noop.py
ibrb/ext/clients/tests/test_system_noop.py
ibrb/ext/clients/tests/test_unit_client_lookup.py
ibrb/ext/clients/tests/test_unit_noop.py
ibrb/ext/clients/web3/__init__.py
ibrb/ext/clients/web3/tests/__init__.py
ibrb/ext/clients/web3/tests/test_integration_common_client.py